datamorph_dag_generator/__init__.py
datamorph_dag_generator/helper_classes.py
datamorph_dag_generator/utils.py
datamorph_dag_generator/workflow_custom_operators.py
datamorph_dag_generator/workflow_dag_builder.py
datamorph_dag_generator/workflow_dag_factory.py
datamorph_workflow_generator-0.0.3.dist-info/METADATA
datamorph_workflow_generator-0.0.3.dist-info/WHEEL
datamorph_workflow_generator-0.0.3.dist-info/top_level.txt
datamorph_workflow_generator-0.0.3.dist-info/RECORD
