Metadata-Version: 2.1
Name: datamorph-workflow-generator
Version: 0.0.3
Summary: DataMorph Workflow Package
Author: Annapurna Annadatha
Author-email: sowmya@kwartile.com
License: UNKNOWN
Keywords: python,datamorph,workflow,airflow
Platform: UNKNOWN
Classifier: Development Status :: 3 - Alpha
Classifier: Programming Language :: Python :: 3
Classifier: Operating System :: MacOS :: MacOS X
Requires-Python: >=3.6.0
